[{"support": "28.0", "id": 0, "user_ids": ["A1", "A12", "A21", "A3", "A8", "B14", "B15", "B17", "B18", "B19", "B20", "B22", "B23", "B24", "B26", "B27", "B28", "B29", "B32", "B36", "B37", "B39", "B4", "B43", "B44", "B45", "B46", "B48"], "corrected": 16, "pattern": ["Select", "Select", "Select", "Select", "Explore", "Select", "Filter", "Select", "Abstract_Elaborate", "Select"]}, {"support": "27.0", "id": 1, "user_ids": ["A1", "A12", "A21", "A3", "A8", "B14", "B15", "B18", "B19", "B20", "B22", "B23", "B24", "B26", "B27", "B28", "B29", "B32", "B36", "B37", "B39", "B4", "B43", "B44", "B45", "B46", "B48"], "corrected": 15, "pattern": ["Select", "Select", "Select", "Select", "Explore", "Select", "Filter", "Select", "Abstract_Elaborate", "Select", "Abstract_Elaborate", "Select"]}, {"support": "28.0", "id": 2, "user_ids": ["A13", "A15", "A16", "A22", "A6", "A8", "A9", "B12", "B14", "B15", "B16", "B18", "B19", "B20", "B21", "B24", "B27", "B28", "B34", "B35", "B36", "B37", "B39", "B40", "B42", "B43", "B45", "B46"], "corrected": 19, "pattern": ["Select", "Select", "Select", "Select", "Explore", "Select", "Filter", "Select", "Filter", "Select"]}, {"support": "45.0", "id": 3, "user_ids": ["A1", "A12", "A13", "A15", "A16", "A18", "A20", "A21", "A22", "A3", "A6", "A8", "A9", "B12", "B14", "B15", "B16", "B17", "B18", "B19", "B20", "B22", "B23", "B24", "B26", "B27", "B28", "B29", "B31", "B32", "B33", "B34", "B35", "B36", "B37", "B39", "B4", "B40", "B41", "B42", "B43", "B44", "B45", "B46", "B48"], "corrected": 29, "pattern": ["Select", "Select", "Select", "Select", "Explore", "Select", "History_Br", "Select", "Filter", "Select"]}, {"support": "32.0", "id": 4, "user_ids": ["A1", "A12", "A15", "A21", "A3", "A6", "A8", "B14", "B15", "B17", "B18", "B19", "B20", "B22", "B23", "B24", "B26", "B27", "B28", "B29", "B32", "B35", "B36", "B37", "B39", "B4", "B42", "B43", "B44", "B45", "B46", "B48"], "corrected": 20, "pattern": ["Select", "Select", "Select", "Select", "Explore", "Select", "History_Br", "Select", "Filter", "Select", "Abstract_Elaborate", "Select"]}, {"support": "30.0", "id": 5, "user_ids": ["A1", "A12", "A15", "A21", "A3", "A8", "B14", "B15", "B18", "B19", "B20", "B22", "B23", "B24", "B26", "B27", "B28", "B29", "B32", "B35", "B36", "B37", "B39", "B4", "B42", "B43", "B44", "B45", "B46", "B48"], "corrected": 18, "pattern": ["Select", "Select", "Select", "Select", "Explore", "Select", "History_Br", "Select", "Filter", "Select", "Abstract_Elaborate", "Select", "Abstract_Elaborate", "Select"]}, {"support": "29.0", "id": 6, "user_ids": ["A13", "A15", "A16", "A20", "A22", "A6", "A8", "A9", "B12", "B14", "B15", "B16", "B17", "B18", "B19", "B20", "B27", "B28", "B33", "B34", "B35", "B36", "B37", "B39", "B40", "B42", "B43", "B45", "B46"], "corrected": 20, "pattern": ["Select", "Select", "Select", "Select", "Explore", "Select", "History_Br", "Select", "Filter", "Select", "Filter", "Select"]}, {"support": "36.0", "id": 7, "user_ids": ["A1", "A11", "A12", "A13", "A14", "A15", "A16", "A18", "A19", "A2", "A21", "A3", "A4", "A5", "A6", "A7", "A8", "B13", "B14", "B15", "B18", "B19", "B20", "B22", "B23", "B24", "B27", "B29", "B32", "B36", "B37", "B43", "B44", "B45", "B46", "B48"], "corrected": 19, "pattern": ["Select", "Select", "Select", "Select", "Filter", "Select", "Abstract_Elaborate", "Select", "Abstract_Elaborate", "Select"]}, {"support": "32.0", "id": 8, "user_ids": ["A1", "A11", "A12", "A13", "A14", "A15", "A16", "A18", "A19", "A2", "A21", "A3", "A4", "A5", "A6", "A7", "A8", "B13", "B14", "B15", "B18", "B19", "B20", "B22", "B24", "B27", "B29", "B32", "B36", "B37", "B45", "B46"], "corrected": 17, "pattern": ["Select", "Select", "Select", "Select", "Filter", "Select", "Abstract_Elaborate", "Select", "Abstract_Elaborate", "Select", "Abstract_Elaborate", "Select"]}, {"support": "31.0", "id": 9, "user_ids": ["A1", "A11", "A12", "A13", "A14", "A15", "A16", "A18", "A19", "A2", "A21", "A3", "A4", "A5", "A6", "A7", "B13", "B14", "B15", "B18", "B19", "B20", "B22", "B24", "B27", "B29", "B32", "B36", "B37", "B45", "B46"], "corrected": 17, "pattern": ["Select", "Select", "Select", "Select", "Filter", "Select", "Abstract_Elaborate", "Select", "Abstract_Elaborate", "Select", "Abstract_Elaborate", "Select", "Abstract_Elaborate", "Select"]}, {"support": "30.0", "id": 10, "user_ids": ["A1", "A11", "A12", "A13", "A14", "A15", "A16", "A18", "A19", "A2", "A21", "A3", "A4", "A5", "A6", "A7", "B13", "B14", "B15", "B18", "B19", "B20", "B22", "B24", "B27", "B29", "B32", "B36", "B37", "B45"], "corrected": 16, "pattern": ["Select", "Select", "Select", "Select", "Filter", "Select", "Abstract_Elaborate", "Select", "Abstract_Elaborate", "Select", "Abstract_Elaborate", "Select", "Abstract_Elaborate", "Select", "Abstract_Elaborate", "Select"]}, {"support": "30.0", "id": 11, "user_ids": ["A1", "A11", "A12", "A13", "A14", "A15", "A16", "A18", "A19", "A2", "A21", "A3", "A4", "A5", "A6", "A7", "B13", "B14", "B15", "B18", "B19", "B20", "B22", "B24", "B27", "B29", "B32", "B36", "B37", "B45"], "corrected": 16, "pattern": ["Select", "Select", "Select", "Select", "Filter", "Select", "Abstract_Elaborate", "Select", "Abstract_Elaborate", "Select", "Abstract_Elaborate", "Select", "Abstract_Elaborate", "Select", "Abstract_Elaborate", "Select", "Abstract_Elaborate", "Select"]}, {"support": "28.0", "id": 12, "user_ids": ["A1", "A12", "A13", "A14", "A15", "A16", "A18", "A19", "A2", "A21", "A3", "A5", "A6", "A7", "B13", "B14", "B15", "B18", "B19", "B20", "B22", "B24", "B27", "B29", "B32", "B36", "B37", "B45"], "corrected": 16, "pattern": ["Select", "Select", "Select", "Select", "Filter", "Select", "Abstract_Elaborate", "Select", "Abstract_Elaborate", "Select", "Abstract_Elaborate", "Select", "Abstract_Elaborate", "Select", "Abstract_Elaborate", "Select", "Abstract_Elaborate", "Select", "Abstract_Elaborate", "Select"]}, {"support": "30.0", "id": 13, "user_ids": ["A1", "A11", "A12", "A19", "A2", "A21", "A3", "A8", "A9", "B13", "B14", "B15", "B16", "B18", "B20", "B22", "B23", "B24", "B26", "B28", "B29", "B32", "B37", "B4", "B41", "B43", "B44", "B45", "B46", "B48"], "corrected": 16, "pattern": ["Select", "Select", "Select", "Select", "History_Br", "Select", "Abstract_Elaborate", "Select", "Abstract_Elaborate", "Select"]}, {"support": "36.0", "id": 14, "user_ids": ["A1", "A11", "A12", "A15", "A19", "A2", "A21", "A3", "A6", "A8", "B13", "B14", "B15", "B17", "B18", "B19", "B20", "B22", "B23", "B24", "B26", "B27", "B28", "B29", "B32", "B35", "B36", "B37", "B39", "B4", "B42", "B43", "B44", "B45", "B46", "B48"], "corrected": 20, "pattern": ["Select", "Select", "Select", "Select", "History_Br", "Select", "Filter", "Select", "Abstract_Elaborate", "Select"]}, {"support": "34.0", "id": 15, "user_ids": ["A1", "A11", "A12", "A15", "A19", "A2", "A21", "A3", "A8", "B13", "B14", "B15", "B18", "B19", "B20", "B22", "B23", "B24", "B26", "B27", "B28", "B29", "B32", "B35", "B36", "B37", "B39", "B4", "B42", "B43", "B44", "B45", "B46", "B48"], "corrected": 18, "pattern": ["Select", "Select", "Select", "Select", "History_Br", "Select", "Filter", "Select", "Abstract_Elaborate", "Select", "Abstract_Elaborate", "Select"]}, {"support": "28.0", "id": 16, "user_ids": ["A1", "A11", "A12", "A15", "A19", "A2", "A21", "A3", "B13", "B14", "B15", "B18", "B19", "B20", "B22", "B24", "B26", "B27", "B28", "B29", "B32", "B35", "B36", "B37", "B4", "B42", "B45", "B46"], "corrected": 16, "pattern": ["Select", "Select", "Select", "Select", "History_Br", "Select", "Filter", "Select", "Abstract_Elaborate", "Select", "Abstract_Elaborate", "Select", "Abstract_Elaborate", "Select"]}, {"support": "27.0", "id": 17, "user_ids": ["A1", "A11", "A12", "A19", "A2", "A21", "A3", "B13", "B14", "B15", "B18", "B19", "B20", "B22", "B24", "B26", "B27", "B28", "B29", "B32", "B35", "B36", "B37", "B4", "B42", "B45", "B46"], "corrected": 15, "pattern": ["Select", "Select", "Select", "Select", "History_Br", "Select", "Filter", "Select", "Abstract_Elaborate", "Select", "Abstract_Elaborate", "Select", "Abstract_Elaborate", "Select", "Abstract_Elaborate", "Select"]}, {"support": "29.0", "id": 18, "user_ids": ["A13", "A15", "A16", "A20", "A22", "A4", "A6", "A8", "A9", "B12", "B14", "B15", "B16", "B17", "B18", "B19", "B27", "B28", "B33", "B34", "B35", "B36", "B37", "B39", "B40", "B42", "B43", "B45", "B46"], "corrected": 19, "pattern": ["Select", "Select", "Select", "Select", "History_Br", "Select", "Filter", "Select", "Filter", "Select"]}, {"support": "30.0", "id": 19, "user_ids": ["A1", "A11", "A12", "A2", "A21", "A3", "A8", "B13", "B14", "B15", "B18", "B19", "B20", "B22", "B23", "B24", "B26", "B27", "B28", "B29", "B32", "B36", "B37", "B39", "B4", "B43", "B44", "B45", "B46", "B48"], "corrected": 15, "pattern": ["Select", "Select", "Explore", "Select", "Filter", "Select", "Abstract_Elaborate", "Select", "Abstract_Elaborate", "Select"]}, {"support": "28.0", "id": 20, "user_ids": ["A1", "A11", "A12", "A2", "A21", "A3", "A8", "A9", "B13", "B14", "B15", "B16", "B18", "B20", "B22", "B23", "B24", "B26", "B28", "B29", "B32", "B37", "B4", "B43", "B44", "B45", "B46", "B48"], "corrected": 16, "pattern": ["Select", "Select", "Explore", "Select", "History_Br", "Select", "Abstract_Elaborate", "Select", "Abstract_Elaborate", "Select"]}, {"support": "35.0", "id": 21, "user_ids": ["A1", "A11", "A12", "A15", "A2", "A21", "A3", "A6", "A8", "B13", "B14", "B15", "B17", "B18", "B19", "B20", "B22", "B23", "B24", "B26", "B27", "B28", "B29", "B32", "B35", "B36", "B37", "B39", "B4", "B42", "B43", "B44", "B45", "B46", "B48"], "corrected": 20, "pattern": ["Select", "Select", "Explore", "Select", "History_Br", "Select", "Filter", "Select", "Abstract_Elaborate", "Select"]}, {"support": "33.0", "id": 22, "user_ids": ["A1", "A11", "A12", "A15", "A2", "A21", "A3", "A8", "B13", "B14", "B15", "B18", "B19", "B20", "B22", "B23", "B24", "B26", "B27", "B28", "B29", "B32", "B35", "B36", "B37", "B39", "B4", "B42", "B43", "B44", "B45", "B46", "B48"], "corrected": 18, "pattern": ["Select", "Select", "Explore", "Select", "History_Br", "Select", "Filter", "Select", "Abstract_Elaborate", "Select", "Abstract_Elaborate", "Select"]}, {"support": "27.0", "id": 23, "user_ids": ["A1", "A11", "A12", "A15", "A2", "A21", "A3", "B13", "B14", "B15", "B18", "B19", "B20", "B22", "B24", "B26", "B27", "B28", "B29", "B32", "B35", "B36", "B37", "B4", "B42", "B45", "B46"], "corrected": 16, "pattern": ["Select", "Select", "Explore", "Select", "History_Br", "Select", "Filter", "Select", "Abstract_Elaborate", "Select", "Abstract_Elaborate", "Select", "Abstract_Elaborate", "Select"]}, {"support": "35.0", "id": 24, "user_ids": ["A13", "A15", "A16", "A20", "A22", "A4", "A6", "A8", "A9", "B12", "B14", "B15", "B16", "B17", "B18", "B19", "B20", "B22", "B27", "B28", "B31", "B32", "B33", "B34", "B35", "B36", "B37", "B39", "B40", "B41", "B42", "B43", "B45", "B46", "B48"], "corrected": 23, "pattern": ["Select", "Select", "Explore", "Select", "History_Br", "Select", "Filter", "Select", "Filter", "Select"]}, {"support": "28.0", "id": 25, "user_ids": ["A13", "A20", "A22", "A4", "A6", "A9", "B12", "B14", "B15", "B16", "B17", "B18", "B22", "B27", "B31", "B32", "B33", "B34", "B35", "B36", "B39", "B40", "B41", "B42", "B43", "B45", "B46", "B48"], "corrected": 20, "pattern": ["Select", "Select", "Explore", "Select", "History_Br", "Select", "Filter", "Select", "Filter", "Select", "Filter", "Select"]}, {"support": "32.0", "id": 26, "user_ids": ["A1", "A11", "A12", "A13", "A14", "A15", "A16", "A18", "A19", "A2", "A21", "A3", "A4", "A5", "A6", "A7", "A8", "B13", "B14", "B15", "B18", "B19", "B20", "B22", "B24", "B27", "B29", "B32", "B36", "B37", "B45", "B46"], "corrected": 17, "pattern": ["Select", "Select", "Filter", "Select", "Abstract_Elaborate", "Select", "Abstract_Elaborate", "Select", "Abstract_Elaborate", "Select"]}, {"support": "31.0", "id": 27, "user_ids": ["A1", "A11", "A12", "A13", "A14", "A15", "A16", "A18", "A19", "A2", "A21", "A3", "A4", "A5", "A6", "A7", "B13", "B14", "B15", "B18", "B19", "B20", "B22", "B24", "B27", "B29", "B32", "B36", "B37", "B45", "B46"], "corrected": 17, "pattern": ["Select", "Select", "Filter", "Select", "Abstract_Elaborate", "Select", "Abstract_Elaborate", "Select", "Abstract_Elaborate", "Select", "Abstract_Elaborate", "Select"]}, {"support": "30.0", "id": 28, "user_ids": ["A1", "A11", "A12", "A13", "A14", "A15", "A16", "A18", "A19", "A2", "A21", "A3", "A4", "A5", "A6", "A7", "B13", "B14", "B15", "B18", "B19", "B20", "B22", "B24", "B27", "B29", "B32", "B36", "B37", "B45"], "corrected": 16, "pattern": ["Select", "Select", "Filter", "Select", "Abstract_Elaborate", "Select", "Abstract_Elaborate", "Select", "Abstract_Elaborate", "Select", "Abstract_Elaborate", "Select", "Abstract_Elaborate", "Select"]}, {"support": "30.0", "id": 29, "user_ids": ["A1", "A11", "A12", "A13", "A14", "A15", "A16", "A18", "A19", "A2", "A21", "A3", "A4", "A5", "A6", "A7", "B13", "B14", "B15", "B18", "B19", "B20", "B22", "B24", "B27", "B29", "B32", "B36", "B37", "B45"], "corrected": 16, "pattern": ["Select", "Select", "Filter", "Select", "Abstract_Elaborate", "Select", "Abstract_Elaborate", "Select", "Abstract_Elaborate", "Select", "Abstract_Elaborate", "Select", "Abstract_Elaborate", "Select", "Abstract_Elaborate", "Select"]}, {"support": "28.0", "id": 30, "user_ids": ["A1", "A12", "A13", "A14", "A15", "A16", "A18", "A19", "A2", "A21", "A3", "A5", "A6", "A7", "B13", "B14", "B15", "B18", "B19", "B20", "B22", "B24", "B27", "B29", "B32", "B36", "B37", "B45"], "corrected": 16, "pattern": ["Select", "Select", "Filter", "Select", "Abstract_Elaborate", "Select", "Abstract_Elaborate", "Select", "Abstract_Elaborate", "Select", "Abstract_Elaborate", "Select", "Abstract_Elaborate", "Select", "Abstract_Elaborate", "Select", "Abstract_Elaborate", "Select"]}, {"support": "34.0", "id": 31, "user_ids": ["A1", "A11", "A12", "A15", "A19", "A2", "A21", "A3", "A8", "B13", "B14", "B15", "B18", "B19", "B20", "B22", "B23", "B24", "B26", "B27", "B28", "B29", "B32", "B35", "B36", "B37", "B39", "B4", "B42", "B43", "B44", "B45", "B46", "B48"], "corrected": 18, "pattern": ["Select", "Select", "History_Br", "Select", "Filter", "Select", "Abstract_Elaborate", "Select", "Abstract_Elaborate", "Select"]}, {"support": "28.0", "id": 32, "user_ids": ["A1", "A11", "A12", "A15", "A19", "A2", "A21", "A3", "B13", "B14", "B15", "B18", "B19", "B20", "B22", "B24", "B26", "B27", "B28", "B29", "B32", "B35", "B36", "B37", "B4", "B42", "B45", "B46"], "corrected": 16, "pattern": ["Select", "Select", "History_Br", "Select", "Filter", "Select", "Abstract_Elaborate", "Select", "Abstract_Elaborate", "Select", "Abstract_Elaborate", "Select"]}, {"support": "27.0", "id": 33, "user_ids": ["A1", "A11", "A12", "A19", "A2", "A21", "A3", "B13", "B14", "B15", "B18", "B19", "B20", "B22", "B24", "B26", "B27", "B28", "B29", "B32", "B35", "B36", "B37", "B4", "B42", "B45", "B46"], "corrected": 15, "pattern": ["Select", "Select", "History_Br", "Select", "Filter", "Select", "Abstract_Elaborate", "Select", "Abstract_Elaborate", "Select", "Abstract_Elaborate", "Select", "Abstract_Elaborate", "Select"]}, {"support": "28.0", "id": 34, "user_ids": ["A13", "A20", "A22", "A4", "A6", "A9", "B12", "B14", "B15", "B16", "B17", "B18", "B22", "B27", "B31", "B32", "B33", "B34", "B35", "B36", "B39", "B40", "B41", "B42", "B43", "B45", "B46", "B48"], "corrected": 20, "pattern": ["Select", "Select", "History_Br", "Select", "Filter", "Select", "Filter", "Select", "Filter", "Select"]}, {"support": "33.0", "id": 35, "user_ids": ["A1", "A11", "A12", "A15", "A2", "A21", "A3", "A8", "B13", "B14", "B15", "B18", "B19", "B20", "B22", "B23", "B24", "B26", "B27", "B28", "B29", "B32", "B35", "B36", "B37", "B39", "B4", "B42", "B43", "B44", "B45", "B46", "B48"], "corrected": 18, "pattern": ["Explore", "Select", "History_Br", "Select", "Filter", "Select", "Abstract_Elaborate", "Select", "Abstract_Elaborate", "Select"]}, {"support": "27.0", "id": 36, "user_ids": ["A1", "A11", "A12", "A15", "A2", "A21", "A3", "B13", "B14", "B15", "B18", "B19", "B20", "B22", "B24", "B26", "B27", "B28", "B29", "B32", "B35", "B36", "B37", "B4", "B42", "B45", "B46"], "corrected": 16, "pattern": ["Explore", "Select", "History_Br", "Select", "Filter", "Select", "Abstract_Elaborate", "Select", "Abstract_Elaborate", "Select", "Abstract_Elaborate", "Select"]}, {"support": "29.0", "id": 37, "user_ids": ["A13", "A20", "A22", "A4", "A6", "A9", "B12", "B14", "B15", "B16", "B17", "B18", "B20", "B22", "B27", "B31", "B32", "B33", "B34", "B35", "B36", "B39", "B40", "B41", "B42", "B43", "B45", "B46", "B48"], "corrected": 21, "pattern": ["Explore", "Select", "History_Br", "Select", "Filter", "Select", "Filter", "Select", "Filter", "Select"]}, {"support": "46.0", "id": 38, "user_ids": ["A1", "A11", "A12", "A13", "A14", "A15", "A16", "A18", "A19", "A2", "A20", "A21", "A22", "A3", "A4", "A5", "A6", "A7", "A9", "B13", "B14", "B15", "B16", "B17", "B18", "B19", "B20", "B21", "B22", "B24", "B27", "B28", "B29", "B31", "B32", "B33", "B34", "B35", "B36", "B37", "B4", "B40", "B41", "B42", "B43", "B45"], "corrected": 27, "pattern": ["Abstract_Elaborate", "Select", "Abstract_Elaborate", "Select", "Abstract_Elaborate", "Select", "Abstract_Elaborate", "Select", "Abstract_Elaborate", "Select"]}, {"support": "46.0", "id": 39, "user_ids": ["A1", "A11", "A12", "A13", "A14", "A15", "A16", "A18", "A19", "A2", "A20", "A21", "A22", "A3", "A4", "A5", "A6", "A7", "A9", "B13", "B14", "B15", "B16", "B17", "B18", "B19", "B20", "B21", "B22", "B24", "B27", "B28", "B29", "B31", "B32", "B33", "B34", "B35", "B36", "B37", "B4", "B40", "B41", "B42", "B43", "B45"], "corrected": 27, "pattern": ["Abstract_Elaborate", "Select", "Abstract_Elaborate", "Select", "Abstract_Elaborate", "Select", "Abstract_Elaborate", "Select", "Abstract_Elaborate", "Select", "Abstract_Elaborate", "Select"]}, {"support": "42.0", "id": 40, "user_ids": ["A1", "A12", "A13", "A14", "A15", "A16", "A18", "A19", "A2", "A20", "A21", "A22", "A3", "A5", "A6", "A7", "A9", "B13", "B14", "B15", "B16", "B18", "B19", "B20", "B21", "B22", "B24", "B27", "B28", "B29", "B31", "B32", "B33", "B34", "B35", "B36", "B37", "B4", "B41", "B42", "B43", "B45"], "corrected": 25, "pattern": ["Abstract_Elaborate", "Select", "Abstract_Elaborate", "Select", "Abstract_Elaborate", "Select", "Abstract_Elaborate", "Select", "Abstract_Elaborate", "Select", "Abstract_Elaborate", "Select", "Abstract_Elaborate", "Select"]}, {"support": "41.0", "id": 41, "user_ids": ["A1", "A12", "A13", "A14", "A15", "A16", "A18", "A19", "A2", "A20", "A21", "A22", "A3", "A5", "A6", "A7", "A9", "B14", "B15", "B16", "B18", "B19", "B20", "B21", "B22", "B24", "B27", "B28", "B29", "B31", "B32", "B33", "B34", "B35", "B36", "B37", "B4", "B41", "B42", "B43", "B45"], "corrected": 25, "pattern": ["Abstract_Elaborate", "Select", "Abstract_Elaborate", "Select", "Abstract_Elaborate", "Select", "Abstract_Elaborate", "Select", "Abstract_Elaborate", "Select", "Abstract_Elaborate", "Select", "Abstract_Elaborate", "Select", "Abstract_Elaborate", "Select"]}, {"support": "37.0", "id": 42, "user_ids": ["A12", "A13", "A15", "A16", "A18", "A2", "A20", "A21", "A22", "A3", "A5", "A7", "A9", "B14", "B15", "B16", "B18", "B19", "B20", "B21", "B22", "B24", "B27", "B28", "B29", "B31", "B32", "B33", "B34", "B35", "B36", "B37", "B4", "B41", "B42", "B43", "B45"], "corrected": 23, "pattern": ["Abstract_Elaborate", "Select", "Abstract_Elaborate", "Select", "Abstract_Elaborate", "Select", "Abstract_Elaborate", "Select", "Abstract_Elaborate", "Select", "Abstract_Elaborate", "Select", "Abstract_Elaborate", "Select", "Abstract_Elaborate", "Select", "Abstract_Elaborate", "Select"]}, {"support": "36.0", "id": 43, "user_ids": ["A12", "A13", "A15", "A16", "A18", "A2", "A20", "A21", "A3", "A5", "A7", "A9", "B14", "B15", "B16", "B18", "B19", "B20", "B21", "B22", "B24", "B27", "B28", "B29", "B31", "B32", "B33", "B34", "B35", "B36", "B37", "B4", "B41", "B42", "B43", "B45"], "corrected": 23, "pattern": ["Abstract_Elaborate", "Select", "Abstract_Elaborate", "Select", "Abstract_Elaborate", "Select", "Abstract_Elaborate", "Select", "Abstract_Elaborate", "Select", "Abstract_Elaborate", "Select", "Abstract_Elaborate", "Select", "Abstract_Elaborate", "Select", "Abstract_Elaborate", "Select", "Abstract_Elaborate", "Select"]}, {"support": "34.0", "id": 44, "user_ids": ["A12", "A13", "A15", "A16", "A18", "A2", "A20", "A21", "A3", "A5", "A7", "A9", "B14", "B15", "B16", "B18", "B19", "B20", "B21", "B22", "B24", "B27", "B28", "B29", "B31", "B32", "B34", "B35", "B36", "B37", "B4", "B41", "B42", "B45"], "corrected": 22, "pattern": ["Abstract_Elaborate", "Select", "Abstract_Elaborate", "Select", "Abstract_Elaborate", "Select", "Abstract_Elaborate", "Select", "Abstract_Elaborate", "Select", "Abstract_Elaborate", "Select", "Abstract_Elaborate", "Select", "Abstract_Elaborate", "Select", "Abstract_Elaborate", "Select", "Abstract_Elaborate", "Select", "Abstract_Elaborate", "Select"]}, {"support": "33.0", "id": 45, "user_ids": ["A12", "A13", "A15", "A16", "A18", "A2", "A20", "A21", "A3", "A5", "A7", "A9", "B14", "B15", "B16", "B18", "B19", "B20", "B22", "B24", "B27", "B28", "B29", "B31", "B32", "B34", "B35", "B36", "B37", "B4", "B41", "B42", "B45"], "corrected": 22, "pattern": ["Abstract_Elaborate", "Select", "Abstract_Elaborate", "Select", "Abstract_Elaborate", "Select", "Abstract_Elaborate", "Select", "Abstract_Elaborate", "Select", "Abstract_Elaborate", "Select", "Abstract_Elaborate", "Select", "Abstract_Elaborate", "Select", "Abstract_Elaborate", "Select", "Abstract_Elaborate", "Select", "Abstract_Elaborate", "Select", "Abstract_Elaborate", "Select"]}, {"support": "28.0", "id": 46, "user_ids": ["A1", "A12", "A13", "A16", "A18", "A20", "A21", "A22", "A3", "A5", "A7", "A9", "B14", "B15", "B16", "B18", "B20", "B21", "B22", "B24", "B27", "B31", "B32", "B35", "B36", "B41", "B42", "B45"], "corrected": 19, "pattern": ["Abstract_Elaborate", "Select", "Abstract_Elaborate", "Select", "Abstract_Elaborate", "Select", "Abstract_Elaborate", "Select", "Abstract_Elaborate", "Select", "Abstract_Elaborate", "Select", "Filter", "Select"]}, {"support": "29.0", "id": 47, "user_ids": ["A1", "A12", "A13", "A16", "A18", "A20", "A21", "A22", "A3", "A4", "A5", "A7", "A9", "B14", "B15", "B16", "B18", "B20", "B21", "B22", "B24", "B27", "B31", "B32", "B35", "B36", "B41", "B42", "B45"], "corrected": 19, "pattern": ["Abstract_Elaborate", "Select", "Abstract_Elaborate", "Select", "Abstract_Elaborate", "Select", "Abstract_Elaborate", "Select", "Abstract_Elaborate", "Select", "Filter", "Select"]}, {"support": "30.0", "id": 48, "user_ids": ["A1", "A12", "A13", "A16", "A18", "A20", "A21", "A22", "A3", "A4", "A5", "A6", "A7", "A9", "B14", "B15", "B16", "B18", "B20", "B21", "B22", "B24", "B27", "B31", "B32", "B35", "B36", "B41", "B42", "B45"], "corrected": 20, "pattern": ["Abstract_Elaborate", "Select", "Abstract_Elaborate", "Select", "Abstract_Elaborate", "Select", "Abstract_Elaborate", "Select", "Filter", "Select"]}, {"support": "28.0", "id": 49, "user_ids": ["A1", "A13", "A14", "A16", "A18", "A19", "A20", "A21", "A22", "A3", "A4", "A5", "A6", "A9", "B14", "B15", "B20", "B22", "B24", "B26", "B27", "B31", "B32", "B34", "B36", "B41", "B42", "B45"], "corrected": 16, "pattern": ["Abstract_Elaborate", "Select", "Abstract_Elaborate", "Select", "Abstract_Elaborate", "Select", "Abstract_Elaborate", "Select", "Annotation", "Select"]}, {"support": "49.0", "id": 50, "user_ids": ["A1", "A11", "A12", "A13", "A14", "A15", "A16", "A18", "A19", "A2", "A20", "A21", "A22", "A3", "A4", "A5", "A6", "A7", "A9", "B13", "B14", "B15", "B16", "B17", "B18", "B19", "B20", "B21", "B22", "B24", "B26", "B27", "B28", "B29", "B31", "B32", "B33", "B34", "B35", "B36", "B37", "B4", "B40", "B41", "B42", "B43", "B45", "B46", "B48"], "corrected": 29, "pattern": ["Filter", "Select", "Abstract_Elaborate", "Select", "Abstract_Elaborate", "Select", "Abstract_Elaborate", "Select", "Abstract_Elaborate", "Select"]}, {"support": "46.0", "id": 51, "user_ids": ["A1", "A11", "A12", "A13", "A14", "A15", "A16", "A18", "A19", "A2", "A20", "A21", "A22", "A3", "A4", "A5", "A6", "A7", "A9", "B13", "B14", "B15", "B16", "B17", "B18", "B19", "B20", "B21", "B22", "B24", "B27", "B28", "B29", "B31", "B32", "B33", "B34", "B35", "B36", "B37", "B4", "B40", "B41", "B42", "B43", "B45"], "corrected": 27, "pattern": ["Filter", "Select", "Abstract_Elaborate", "Select", "Abstract_Elaborate", "Select", "Abstract_Elaborate", "Select", "Abstract_Elaborate", "Select", "Abstract_Elaborate", "Select"]}, {"support": "46.0", "id": 52, "user_ids": ["A1", "A11", "A12", "A13", "A14", "A15", "A16", "A18", "A19", "A2", "A20", "A21", "A22", "A3", "A4", "A5", "A6", "A7", "A9", "B13", "B14", "B15", "B16", "B17", "B18", "B19", "B20", "B21", "B22", "B24", "B27", "B28", "B29", "B31", "B32", "B33", "B34", "B35", "B36", "B37", "B4", "B40", "B41", "B42", "B43", "B45"], "corrected": 27, "pattern": ["Filter", "Select", "Abstract_Elaborate", "Select", "Abstract_Elaborate", "Select", "Abstract_Elaborate", "Select", "Abstract_Elaborate", "Select", "Abstract_Elaborate", "Select", "Abstract_Elaborate", "Select"]}, {"support": "42.0", "id": 53, "user_ids": ["A1", "A12", "A13", "A14", "A15", "A16", "A18", "A19", "A2", "A20", "A21", "A22", "A3", "A5", "A6", "A7", "A9", "B13", "B14", "B15", "B16", "B18", "B19", "B20", "B21", "B22", "B24", "B27", "B28", "B29", "B31", "B32", "B33", "B34", "B35", "B36", "B37", "B4", "B41", "B42", "B43", "B45"], "corrected": 25, "pattern": ["Filter", "Select", "Abstract_Elaborate", "Select", "Abstract_Elaborate", "Select", "Abstract_Elaborate", "Select", "Abstract_Elaborate", "Select", "Abstract_Elaborate", "Select", "Abstract_Elaborate", "Select", "Abstract_Elaborate", "Select"]}, {"support": "41.0", "id": 54, "user_ids": ["A1", "A12", "A13", "A14", "A15", "A16", "A18", "A19", "A2", "A20", "A21", "A22", "A3", "A5", "A6", "A7", "A9", "B14", "B15", "B16", "B18", "B19", "B20", "B21", "B22", "B24", "B27", "B28", "B29", "B31", "B32", "B33", "B34", "B35", "B36", "B37", "B4", "B41", "B42", "B43", "B45"], "corrected": 25, "pattern": ["Filter", "Select", "Abstract_Elaborate", "Select", "Abstract_Elaborate", "Select", "Abstract_Elaborate", "Select", "Abstract_Elaborate", "Select", "Abstract_Elaborate", "Select", "Abstract_Elaborate", "Select", "Abstract_Elaborate", "Select", "Abstract_Elaborate", "Select"]}, {"support": "37.0", "id": 55, "user_ids": ["A12", "A13", "A15", "A16", "A18", "A2", "A20", "A21", "A22", "A3", "A5", "A7", "A9", "B14", "B15", "B16", "B18", "B19", "B20", "B21", "B22", "B24", "B27", "B28", "B29", "B31", "B32", "B33", "B34", "B35", "B36", "B37", "B4", "B41", "B42", "B43", "B45"], "corrected": 23, "pattern": ["Filter", "Select", "Abstract_Elaborate", "Select", "Abstract_Elaborate", "Select", "Abstract_Elaborate", "Select", "Abstract_Elaborate", "Select", "Abstract_Elaborate", "Select", "Abstract_Elaborate", "Select", "Abstract_Elaborate", "Select", "Abstract_Elaborate", "Select", "Abstract_Elaborate", "Select"]}, {"support": "36.0", "id": 56, "user_ids": ["A12", "A13", "A15", "A16", "A18", "A2", "A20", "A21", "A3", "A5", "A7", "A9", "B14", "B15", "B16", "B18", "B19", "B20", "B21", "B22", "B24", "B27", "B28", "B29", "B31", "B32", "B33", "B34", "B35", "B36", "B37", "B4", "B41", "B42", "B43", "B45"], "corrected": 23, "pattern": ["Filter", "Select", "Abstract_Elaborate", "Select", "Abstract_Elaborate", "Select", "Abstract_Elaborate", "Select", "Abstract_Elaborate", "Select", "Abstract_Elaborate", "Select", "Abstract_Elaborate", "Select", "Abstract_Elaborate", "Select", "Abstract_Elaborate", "Select", "Abstract_Elaborate", "Select", "Abstract_Elaborate", "Select"]}, {"support": "34.0", "id": 57, "user_ids": ["A12", "A13", "A15", "A16", "A18", "A2", "A20", "A21", "A3", "A5", "A7", "A9", "B14", "B15", "B16", "B18", "B19", "B20", "B21", "B22", "B24", "B27", "B28", "B29", "B31", "B32", "B34", "B35", "B36", "B37", "B4", "B41", "B42", "B45"], "corrected": 22, "pattern": ["Filter", "Select", "Abstract_Elaborate", "Select", "Abstract_Elaborate", "Select", "Abstract_Elaborate", "Select", "Abstract_Elaborate", "Select", "Abstract_Elaborate", "Select", "Abstract_Elaborate", "Select", "Abstract_Elaborate", "Select", "Abstract_Elaborate", "Select", "Abstract_Elaborate", "Select", "Abstract_Elaborate", "Select", "Abstract_Elaborate", "Select"]}, {"support": "35.0", "id": 58, "user_ids": ["A1", "A15", "A16", "A18", "A20", "A21", "A22", "A6", "A7", "A9", "B15", "B16", "B17", "B18", "B19", "B21", "B22", "B24", "B27", "B28", "B31", "B32", "B33", "B34", "B35", "B36", "B37", "B4", "B40", "B41", "B42", "B43", "B45", "B46", "B48"], "corrected": 25, "pattern": ["Filter", "Select", "Filter", "Select", "Abstract_Elaborate", "Select", "Abstract_Elaborate", "Select", "Abstract_Elaborate", "Select"]}, {"support": "35.0", "id": 59, "user_ids": ["A1", "A15", "A16", "A18", "A20", "A21", "A22", "A6", "A7", "A9", "B15", "B16", "B17", "B18", "B19", "B21", "B22", "B24", "B27", "B28", "B31", "B32", "B33", "B34", "B35", "B36", "B37", "B4", "B40", "B41", "B42", "B43", "B45", "B46", "B48"], "corrected": 25, "pattern": ["Filter", "Select", "Filter", "Select", "Abstract_Elaborate", "Select", "Abstract_Elaborate", "Select", "Abstract_Elaborate", "Select", "Abstract_Elaborate", "Select"]}, {"support": "33.0", "id": 60, "user_ids": ["A1", "A15", "A16", "A18", "A20", "A21", "A22", "A6", "A7", "A9", "B15", "B16", "B17", "B18", "B19", "B21", "B22", "B24", "B27", "B28", "B31", "B32", "B33", "B34", "B35", "B36", "B37", "B4", "B40", "B41", "B42", "B43", "B45"], "corrected": 23, "pattern": ["Filter", "Select", "Filter", "Select", "Abstract_Elaborate", "Select", "Abstract_Elaborate", "Select", "Abstract_Elaborate", "Select", "Abstract_Elaborate", "Select", "Abstract_Elaborate", "Select"]}, {"support": "33.0", "id": 61, "user_ids": ["A1", "A15", "A16", "A18", "A20", "A21", "A22", "A6", "A7", "A9", "B15", "B16", "B17", "B18", "B19", "B21", "B22", "B24", "B27", "B28", "B31", "B32", "B33", "B34", "B35", "B36", "B37", "B4", "B40", "B41", "B42", "B43", "B45"], "corrected": 23, "pattern": ["Filter", "Select", "Filter", "Select", "Abstract_Elaborate", "Select", "Abstract_Elaborate", "Select", "Abstract_Elaborate", "Select", "Abstract_Elaborate", "Select", "Abstract_Elaborate", "Select", "Abstract_Elaborate", "Select"]}, {"support": "30.0", "id": 62, "user_ids": ["A1", "A15", "A16", "A18", "A20", "A21", "A22", "A6", "A7", "A9", "B16", "B18", "B19", "B21", "B22", "B24", "B27", "B28", "B31", "B32", "B33", "B34", "B35", "B36", "B37", "B4", "B41", "B42", "B43", "B45"], "corrected": 20, "pattern": ["Filter", "Select", "Filter", "Select", "Abstract_Elaborate", "Select", "Abstract_Elaborate", "Select", "Abstract_Elaborate", "Select", "Abstract_Elaborate", "Select", "Abstract_Elaborate", "Select", "Abstract_Elaborate", "Select", "Abstract_Elaborate", "Select"]}, {"support": "28.0", "id": 63, "user_ids": ["A15", "A16", "A18", "A20", "A21", "A22", "A6", "A7", "A9", "B16", "B18", "B19", "B21", "B22", "B24", "B27", "B28", "B31", "B33", "B34", "B35", "B36", "B37", "B4", "B41", "B42", "B43", "B45"], "corrected": 18, "pattern": ["Filter", "Select", "Filter", "Select", "Abstract_Elaborate", "Select", "Abstract_Elaborate", "Select", "Abstract_Elaborate", "Select", "Abstract_Elaborate", "Select", "Abstract_Elaborate", "Select", "Abstract_Elaborate", "Select", "Abstract_Elaborate", "Select", "Abstract_Elaborate", "Select"]}, {"support": "27.0", "id": 64, "user_ids": ["A15", "A16", "A18", "A20", "A21", "A22", "A7", "A9", "B16", "B18", "B19", "B21", "B22", "B24", "B27", "B28", "B31", "B33", "B34", "B35", "B36", "B37", "B4", "B41", "B42", "B43", "B45"], "corrected": 17, "pattern": ["Filter", "Select", "Filter", "Select", "Abstract_Elaborate", "Select", "Abstract_Elaborate", "Select", "Abstract_Elaborate", "Select", "Abstract_Elaborate", "Select", "Abstract_Elaborate", "Select", "Abstract_Elaborate", "Select", "Abstract_Elaborate", "Select", "Abstract_Elaborate", "Select", "Abstract_Elaborate", "Select"]}, {"support": "30.0", "id": 65, "user_ids": ["A1", "A16", "A18", "A20", "A21", "A22", "A7", "A9", "B12", "B15", "B16", "B17", "B18", "B20", "B21", "B22", "B24", "B27", "B32", "B33", "B35", "B36", "B39", "B4", "B40", "B41", "B42", "B43", "B45", "B48"], "corrected": 21, "pattern": ["Filter", "Select", "Filter", "Select", "Filter", "Select", "Abstract_Elaborate", "Select", "Abstract_Elaborate", "Select"]}, {"support": "27.0", "id": 66, "user_ids": ["A1", "A16", "A18", "A20", "A21", "A22", "A7", "A9", "B15", "B16", "B17", "B18", "B21", "B22", "B24", "B27", "B32", "B33", "B35", "B36", "B4", "B40", "B41", "B42", "B43", "B45", "B48"], "corrected": 19, "pattern": ["Filter", "Select", "Filter", "Select", "Filter", "Select", "Abstract_Elaborate", "Select", "Abstract_Elaborate", "Select", "Abstract_Elaborate", "Select"]}, {"support": "28.0", "id": 67, "user_ids": ["A1", "A20", "A21", "A22", "A6", "A7", "A9", "B12", "B16", "B17", "B18", "B20", "B21", "B22", "B24", "B27", "B32", "B33", "B35", "B36", "B39", "B4", "B40", "B41", "B42", "B43", "B45", "B48"], "corrected": 20, "pattern": ["Filter", "Select", "Filter", "Select", "Filter", "Select", "Filter", "Select", "Abstract_Elaborate", "Select"]}, {"support": "27.0", "id": 68, "user_ids": ["A1", "A20", "A21", "A22", "A7", "A9", "B12", "B16", "B17", "B18", "B20", "B21", "B22", "B24", "B27", "B32", "B33", "B35", "B36", "B39", "B4", "B40", "B41", "B42", "B43", "B45", "B48"], "corrected": 19, "pattern": ["Filter", "Select", "Filter", "Select", "Filter", "Select", "Filter", "Select", "Abstract_Elaborate", "Select", "Abstract_Elaborate", "Select"]}, {"support": "28.0", "id": 69, "user_ids": ["A1", "A13", "A15", "A20", "A22", "A7", "A9", "B12", "B15", "B16", "B17", "B18", "B20", "B21", "B22", "B24", "B27", "B31", "B32", "B33", "B34", "B35", "B36", "B40", "B41", "B43", "B45", "B48"], "corrected": 21, "pattern": ["Filter", "Select", "Filter", "Select", "Filter", "Select", "Filter", "Select", "Filter", "Select"]}, {"support": "29.0", "id": 70, "user_ids": ["A1", "A11", "A12", "A15", "A19", "A2", "A21", "A3", "B13", "B14", "B15", "B18", "B19", "B20", "B22", "B24", "B26", "B27", "B28", "B29", "B32", "B35", "B36", "B37", "B4", "B41", "B42", "B45", "B46"], "corrected": 16, "pattern": ["History_Br", "Select", "Filter", "Select", "Abstract_Elaborate", "Select", "Abstract_Elaborate", "Select", "Abstract_Elaborate", "Select"]}, {"support": "28.0", "id": 71, "user_ids": ["A1", "A11", "A12", "A19", "A2", "A21", "A3", "B13", "B14", "B15", "B18", "B19", "B20", "B22", "B24", "B26", "B27", "B28", "B29", "B32", "B35", "B36", "B37", "B4", "B41", "B42", "B45", "B46"], "corrected": 15, "pattern": ["History_Br", "Select", "Filter", "Select", "Abstract_Elaborate", "Select", "Abstract_Elaborate", "Select", "Abstract_Elaborate", "Select", "Abstract_Elaborate", "Select"]}]