{"request": [{"vis_types": "Scatter Plot", "data": "text", "project_name": "experiment", "parent_block_ver": 0, "block_iden": "U-1502976535370", "data_annotation": null, "block_ver": 0, "session_ver": 0, "parent_block_iden": null, "selected_index": "[]", "brushed_range": "[[0,0],[0,0]]", "username": "S14", "session_name": "Problem4", "x_axis": "Year", "data_name": "car.csv (17.46 KB)", "block_name": "2", "y_axis": "Year"}], "response": [{"vis_types": "Scatter Plot", "brushed_range": "[[0,0],[0,0]]", "annotation_path": "static/member/S14/experiment/Problem4/0/U-1502976535370/annotation.json", "data": "text", "block_ver": 0, "x_axis": "Year", "sp_path": "static/member/S14/experiment/Problem4/0/U-1502976535370/0/sp.json", "y_axis": "Year", "selected_index": "[]"}], "position": {"top": 244, "width": 1052, "left": 519, "height": 0}}