{"position": {"left": 0, "width": 1038.5, "top": 0, "height": 0}, "response": [{"annotation_path": "static/member/S1/My Project/Problem 1/0/U-1505748077356/annotation.json", "data": "text", "column_order": "[\"1\",\"2\",\"8\",\"3\",\"4\",\"5\",\"6\",\"7\"]", "pcp_path": "static/member/S1/My Project/Problem 1/0/U-1505748077356/0/pcp.json", "selected_index": "[118,140]", "brushed_range": "[[0,0],[0,0],[164.62025451660156,196.10386657714844],[0,0],[0,0],[0,0],[0,0],[64.51117706298828,92.8464126586914]]", "brushed_axis": "[0,0,1,0,0,0,0,1]", "vis_types": "Parallel Coordinate Plot", "block_ver": 0}], "request": [{"parent_block_ver": 0, "data_name": "car.csv (17.46 KB)", "session_ver": 0, "session_name": "Problem 1", "selected_index": "[118,140]", "vis_types": "Parallel Coordinate Plot", "block_ver": 0, "parent_block_iden": null, "data": "text", "username": "S1", "column_order": "[\"1\",\"2\",\"8\",\"3\",\"4\",\"5\",\"6\",\"7\"]", "brushed_range": "[[0,0],[0,0],[164.62025451660156,196.10386657714844],[0,0],[0,0],[0,0],[0,0],[64.51117706298828,92.8464126586914]]", "brushed_axis": "[0,0,1,0,0,0,0,1]", "block_name": "1-B#41", "block_iden": "U-1505748077356", "data_annotation": null, "project_name": "My Project"}]}