{"response": [{"annotation_path": "static/member/A19/experiment /Problem 1/0/U-1490588467703/annotation.json", "block_ver": 0, "vis_types": "Scatter Plot", "sp_path": "static/member/A19/experiment /Problem 1/0/U-1490588467703/0/sp.json", "x_axis": "Power (hp)", "data": "text", "brushed_range": "[[0,0],[0,0]]", "y_axis": "Weight (lb)"}], "position": {"width": 1039.55214203125, "top": 33.9756965637207, "height": 1084.6250180078125, "left": 226.9791259765625}, "request": [{"data_name": "car.csv (17.46 KB)", "parent_block_ver": 0, "project_name": "experiment ", "vis_types": "Scatter Plot", "data": "text", "block_iden": "U-1490588467703", "parent_block_iden": null, "data_annotation": null, "block_name": "2", "session_name": "Problem 1", "brushed_range": "[[0,0],[0,0]]", "block_ver": 0, "x_axis": "Power (hp)", "username": "A19", "y_axis": "Weight (lb)", "session_ver": 0}]}