{"request": [{"block_iden": "U-1522154745347", "brushed_range": "[[65.410400390625,111.16508865356445],[0,0],[0,0],[0,0],[0,0],[0,0],[0,0],[95.97957611083984,287.2107238769531]]", "session_name": "for tree", "vis_types": "Parallel Coordinate Plot", "data_name": "car.csv (17.46 KB)", "block_name": "1-B#21", "username": "S1", "data_annotation": null, "column_order": "[\"1\",\"5\",\"8\",\"2\",\"3\",\"4\",\"6\",\"7\"]", "project_name": "New Project", "session_ver": 1, "selected_index": "[57,58,61,62,69,72,73,74,78,79,84,86,87,88,91,94,95,101,102,105,108]", "block_ver": 0, "parent_block_iden": null, "parent_block_ver": 0, "data": "text", "brushed_axis": "[1,0,0,0,0,0,0,1]"}], "response": [{"selected_index": "", "brushed_range": "[[65.410400390625,111.16508865356445],[0,0],[0,0],[0,0],[0,0],[0,0],[0,0],[95.97957611083984,287.2107238769531]]", "vis_types": "Parallel Coordinate Plot", "block_ver": 0, "data": "text", "column_order": "[\"1\",\"5\",\"8\",\"2\",\"3\",\"4\",\"6\",\"7\"]", "pcp_path": "static/member/S1/New Project/3-1/0/U-1522154745347/0/pcp.json", "brushed_axis": "[1,0,0,0,0,0,0,1]", "annotation_path": "static/member/S1/New Project/3-1/0/U-1522154745347/0/annotation.json"}], "position": {"left": 0, "height": 0, "width": 851, "top": 132}}