{"response": [{"data": "text", "selected_index": "[]", "x_axis": "Weight (lb)", "annotation_path": "static/member/S1/SANKEY PROCESS/server_0322/0/U-1521724506831/annotation.json", "sp_path": "static/member/S1/SANKEY PROCESS/server_0322/0/U-1521724506831/0/sp.json", "block_ver": 0, "brushed_range": "[[0,0],[0,0]]", "vis_types": "Scatter Plot", "y_axis": "Power (hp)"}], "request": [{"selected_index": "[]", "block_name": "5", "session_ver": 0, "parent_block_iden": null, "session_name": "server_0322", "brushed_range": "[[0,0],[0,0]]", "parent_block_ver": 0, "data_annotation": null, "data": "text", "project_name": "SANKEY PROCESS", "username": "S1", "vis_types": "Scatter Plot", "x_axis": "Weight (lb)", "block_ver": 0, "block_iden": "U-1521724506831", "data_name": "car.csv (17.46 KB)", "y_axis": "Power (hp)"}], "position": {"width": 226.7329444042969, "height": -1.9915771485301548e-06, "top": 220.58238220214844, "left": 810.9375}}