{"request": [{"data_name": "car.csv (17.46 KB)", "project_name": "experiment", "vis_types": "Parallel Coordinate Plot", "column_order": "[\"1\",\"2\",\"3\",\"4\",\"5\",\"6\",\"7\",\"8\"]", "session_ver": 0, "parent_block_ver": 0, "data_annotation": null, "brushed_axis": "[1,0,0,0,0,0,0,1]", "brushed_range": "[[270.59063720703125,284.3564453125],[0,0],[0,0],[0,0],[0,0],[0,0],[0,0],[105.75759887695312,127.88257598876953]]", "selected_index": "[]", "data": "text", "block_ver": 0, "parent_block_iden": null, "block_name": "4", "block_iden": "U-1490515914092", "username": "B27", "session_name": "Problem 4"}], "response": [{"block_ver": 0, "brushed_range": "[[270.59063720703125,284.3564453125],[0,0],[0,0],[0,0],[0,0],[0,0],[0,0],[105.75759887695312,127.88257598876953]]", "vis_types": "Parallel Coordinate Plot", "pcp_path": "static/member/B27/experiment/Problem 4/0/U-1490515914092/0/pcp.json", "brushed_axis": "[1,0,0,0,0,0,0,1]", "column_order": "[\"1\",\"2\",\"3\",\"4\",\"5\",\"6\",\"7\",\"8\"]", "annotation_path": "static/member/B27/experiment/Problem 4/0/U-1490515914092/annotation.json", "selected_index": "[]", "data": "text"}], "position": {"height": 439, "top": 22, "left": 909.65625, "width": 698.109375}}