{"request": [{"block_ver": 0, "parent_block_iden": null, "data": "text", "block_iden": "U-3419", "y_axis": "Power (hp)", "block_name": "1", "data_name": "car.csv (17.46 KB)", "brushed_range": "[[468.912109375,0],[774.4134521484375,957.4270324707031]]", "username": "A18", "parent_block_ver": 0, "x_axis": "Year", "session_name": "problem 3", "session_ver": 0, "vis_types": "Scatter Plot", "data_annotation": null, "project_name": "experiment"}], "response": [{"block_ver": 0, "x_axis": "Year", "sp_path": "static/member/A18/experiment/problem 3/0/U-3419/0/sp.json", "y_axis": "Power (hp)", "data": "text", "annotation_path": "static/member/A18/experiment/problem 3/0/U-3419/annotation.json", "brushed_range": "[[468.912109375,0],[774.4134521484375,957.4270324707031]]", "vis_types": "Scatter Plot"}], "position": {"top": 24, "width": 692.0625, "height": 0, "left": 96}}