{"response": [{"brushed_range": "[[409.957763671875,417.16302490234375],[0,0],[0,0],[0,0],[0,0],[0,0],[0,0],[0,0]]", "data": "text", "block_ver": 0, "annotation_path": "static/member/B8/experiment/problem 4/0/U-9692/annotation.json", "brushed_axis": "[1,0,0,0,0,0,0,0]", "pcp_path": "static/member/B8/experiment/problem 4/0/U-9692/0/pcp.json", "vis_types": "Parallel Coordinate Plot", "selected_index": "[350,351,352,353,354,355,356,357,358,359,360,361,362,363,364,365,366,367,368,369,370,371,372,373,374,375]", "column_order": "[\"1\",\"2\",\"3\",\"4\",\"5\",\"6\",\"7\",\"8\"]"}], "position": {"left": 678.09375, "top": 428, "height": 608, "width": 1038.09375}, "request": [{"brushed_range": "[[409.957763671875,417.16302490234375],[0,0],[0,0],[0,0],[0,0],[0,0],[0,0],[0,0]]", "block_iden": "U-9692", "session_name": "problem 4", "data": "text", "session_ver": 0, "project_name": "experiment", "selected_index": "[350,351,352,353,354,355,356,357,358,359,360,361,362,363,364,365,366,367,368,369,370,371,372,373,374,375]", "column_order": "[\"1\",\"2\",\"3\",\"4\",\"5\",\"6\",\"7\",\"8\"]", "username": "B8", "parent_block_iden": "U-4762", "data_name": "car.csv (17.46 KB)", "block_ver": 0, "block_name": "7", "brushed_axis": "[1,0,0,0,0,0,0,0]", "parent_block_ver": "0", "vis_types": "Parallel Coordinate Plot", "data_annotation": null}]}