{"position": {"top": 154, "width": 929, "height": 0, "left": 691}, "response": [{"x_axis": "Weight (lb)", "block_ver": 0, "sp_path": "static/member/A9/experiment/Problem 2/0/U-1490609813811/0/sp.json", "y_axis": "Power (hp)", "data": "text", "annotation_path": "static/member/A9/experiment/Problem 2/0/U-1490609813811/annotation.json", "brushed_range": "[[363.0751953125,13.576883316040039],[493.69677734375,75.99781799316406]]", "vis_types": "Scatter Plot"}], "request": [{"block_ver": 0, "x_axis": "Weight (lb)", "data": "text", "block_iden": "U-1490609813811", "y_axis": "Power (hp)", "block_name": "2", "data_name": "car.csv (17.46 KB)", "parent_block_ver": 0, "username": "A9", "vis_types": "Scatter Plot", "parent_block_iden": null, "session_name": "Problem 2", "session_ver": 0, "brushed_range": "[[363.0751953125,13.576883316040039],[493.69677734375,75.99781799316406]]", "data_annotation": null, "project_name": "experiment"}]}