{"annotation_list":[{"annotation": {"project_name": "experiment", "research_annotation": "audi 5000 103\\n", "organism": "", "block_iden": "U-1490510500331", "session_name": "Problem 3", "session_ver": 0, "cluster_annotation": "", "author": "B24", "username": "B24", "block_ver": 0, "date": "2017-03-26 15:47:30", "platform_name": "", "experiment_type": "", "data_annotation": ""}},{"annotation": {"project_name": "experiment", "research_annotation": "BMW 320i 110\\n", "organism": "", "block_iden": "U-1490510500331", "session_name": "Problem 3", "session_ver": 0, "cluster_annotation": "", "author": "B24", "username": "B24", "block_ver": 0, "date": "2017-03-26 15:48:08", "platform_name": "", "experiment_type": "", "data_annotation": ""}},{"annotation": {"project_name": "experiment", "research_annotation": "Mercedes Benz 280S 120", "organism": "", "block_iden": "U-1490510500331", "session_name": "Problem 3", "session_ver": 0, "cluster_annotation": "", "author": "B24", "username": "B24", "block_ver": 0, "date": "2017-03-26 15:48:48", "platform_name": "", "experiment_type": "", "data_annotation": ""}},{"annotation": {"project_name": "experiment", "research_annotation": "", "organism": "", "block_iden": "U-1490510500331", "session_name": "Problem 3", "session_ver": 0, "cluster_annotation": "", "author": "B24", "username": "B24", "block_ver": 0, "date": "2017-03-26 15:51:12", "platform_name": "", "experiment_type": "", "data_annotation": "Mercedes-Benz 280S"}}]}