{"position": {"top": 0, "width": 836, "height": 0, "left": 0}, "request": [{"parent_block_iden": null, "session_name": "Problem2", "parent_block_ver": 0, "data_name": "car.csv (17.46 KB)", "session_ver": 0, "x_axis": "Weight (lb)", "data_annotation": null, "block_iden": "U-1503016039485", "vis_types": "Scatter Plot", "project_name": "experiment", "data": "text", "brushed_range": "[[481.4114685058594,326.5789489746094],[513.1100463867188,370.9569396972656]]", "block_ver": 0, "y_axis": "Power (hp)", "selected_index": "[49]", "block_name": "1", "username": "S33"}], "response": [{"brushed_range": "[[481.4114685058594,326.5789489746094],[513.1100463867188,370.9569396972656]]", "annotation_path": "static/member/S33/experiment/Problem2/0/U-1503016039485/annotation.json", "data": "text", "x_axis": "Weight (lb)", "sp_path": "static/member/S33/experiment/Problem2/0/U-1503016039485/0/sp.json", "vis_types": "Scatter Plot", "y_axis": "Power (hp)", "selected_index": "[49]", "block_ver": 0}]}