{"response": [{"selected_index": "[]", "data": "text", "brushed_range": "[[0,0],[0,0]]", "annotation_path": "static/member/S46/experiment/Problem5/0/U-1504154233400/annotation.json", "block_ver": 0, "scm_path": "static/member/S46/experiment/Problem5/0/U-1504154233400/0/scm.json", "vis_types": "Scatterplot Matrix", "brushed_axis": "[0,0]"}], "request": [{"selected_index": "[]", "block_name": "2", "session_ver": 0, "parent_block_iden": null, "session_name": "Problem5", "brushed_range": "[[0,0],[0,0]]", "parent_block_ver": 0, "data_annotation": null, "data": "text", "project_name": "experiment", "username": "S46", "vis_types": "Scatterplot Matrix", "block_ver": 0, "brushed_axis": "[0,0]", "block_iden": "U-1504154233400", "data_name": "car.csv (17.46 KB)"}], "position": {"width": 278.4722380078125, "height": 2.3281860350721217e-06, "top": 814.9479370117188, "left": 594.9479331970215}}